scrapy_selenium_enhanced/__init__.py
scrapy_selenium_enhanced/http.py
scrapy_selenium_enhanced/middlewares.py
scrapy_selenium_enhanced-0.1.0.dist-info/licenses/LICENSE
scrapy_selenium_enhanced-0.1.0.dist-info/METADATA
scrapy_selenium_enhanced-0.1.0.dist-info/WHEEL
scrapy_selenium_enhanced-0.1.0.dist-info/top_level.txt
scrapy_selenium_enhanced-0.1.0.dist-info/RECORD
