Metadata-Version: 2.4
Name: scrapy-selenium-enhanced
Version: 0.1.0
Summary: Scrapy with selenium and more
License-Expression: WTFPL
Requires-Python: >=3.13
License-File: LICENSE
Requires-Dist: scrapy>=2.13.3
Requires-Dist: selenium>=4.35.0
Dynamic: license-file
